{
  "repeatItems1": [
    {
      "text1": "Gi tid",
      "text2": "Call out a feature, benefit, or value of your site that can stand on its own.",
      "image1": "https://figma-alpha-api.s3.us-west-2.amazonaws.com/images/bd051595-0fe9-4392-bee8-cf6c575e195f"
    },
    {
      "text1": "Gi penger",
      "text2": "Call out a feature, benefit, or value of your site that can stand on its own.",
      "image1": "https://figma-alpha-api.s3.us-west-2.amazonaws.com/images/387ab704-e1aa-46dd-b49f-92b3a969eba9"
    },
    {
      "text1": "Gi stemmen din",
      "text2": "Call out a feature, benefit, or value of your site that can stand on its own.",
      "image1": "https://figma-alpha-api.s3.us-west-2.amazonaws.com/images/8acd6e52-c688-49cb-b79c-c0adf9563b5b"
    }
  ],
  "repeatItems2": [
    {
      "text1": "2.7M+",
      "text2": "I donasjer",
      "image1": "https://figma-alpha-api.s3.us-west-2.amazonaws.com/images/52929760-da68-441b-b0e4-72831aaf2ce0"
    },
    {
      "text1": "40 000+",
      "text2": "Frivillige",
      "image1": "https://figma-alpha-api.s3.us-west-2.amazonaws.com/images/2ac2fa0e-15f3-4b65-b99c-84aa20384a06"
    },
    {
      "text1": "18 ",
      "text2": "Distrikter",
      "image1": "https://figma-alpha-api.s3.us-west-2.amazonaws.com/images/202a5d35-a4f3-4b3f-a03a-3045b138bce0"
    },
    {
      "text1": "100",
      "text2": "Lokalforeninger",
      "image1": "https://figma-alpha-api.s3.us-west-2.amazonaws.com/images/23d43c66-539e-421d-9a02-8216fc6683e4"
    }
  ]
}